catenp/__init__.py
catenp/catenumpy.py
catenp-0.0.13.dist-info/METADATA
catenp-0.0.13.dist-info/WHEEL
catenp-0.0.13.dist-info/top_level.txt
catenp-0.0.13.dist-info/RECORD
