Metadata-Version: 2.1
Name: catenp
Version: 0.0.13
Summary: Python client for extracting data from CATE archives to numpy arrays
Author-email: Motion Signal Technologies <kit.chambers@motionsignaltechnologies.com>
Project-URL: Homepage, https://github.com/motionsignaltechnologies/cate-numpy
Classifier: Programming Language :: Python :: 3
Classifier: License :: OSI Approved :: BSD License
Classifier: Operating System :: OS Independent
Requires-Python: >=3.10
Requires-Dist: numpy >=1.24.3
Requires-Dist: requests >=2.31.0
